model/VERSION
model/__init__.py
model/config.yml
model/pipeline.py
model/predict.py
model/train_pipeline.py
model/config/__init__.py
model/config/core.py
model/datasets/__init__.py
model/datasets/test.csv
model/datasets/train.csv
model/processing/__init__.py
model/processing/data_manager.py
model/processing/validation.py
model/trained_models/__init__.py
model/trained_models/mobile_price_output_v1.0.6.pkl
tid_my_classification_model-1.0.6.dist-info/METADATA
tid_my_classification_model-1.0.6.dist-info/WHEEL
tid_my_classification_model-1.0.6.dist-info/top_level.txt
tid_my_classification_model-1.0.6.dist-info/RECORD
